eternalblue/__init__.py
eternalblue/conversor.py
eternalblue/diarization.py
eternalblue/eternalBlue.py
eternalblue/transcription.py
eternalblue/utils.py
eternalblue-1.3.1.dist-info/METADATA
eternalblue-1.3.1.dist-info/WHEEL
eternalblue-1.3.1.dist-info/top_level.txt
eternalblue-1.3.1.dist-info/RECORD
